py2pycd/__init__.py
py2pycd-0.0.1.dist-info/METADATA
py2pycd-0.0.1.dist-info/RECORD
py2pycd-0.0.1.dist-info/WHEEL
py2pycd-0.0.1.dist-info/entry_points.txt
py2pycd-0.0.1.dist-info/top_level.txt
