Metadata-Version: 2.1
Name: py2pycd
Version: 0.0.1
Summary: py2pycd
Home-page: https://github.com/luoyeah/py2pycd
Author: luoyeah
Author-email: luoyeah_ilku@foxmail.com
License: GPLv3
Keywords: py,pyc,pyd,py2pyc,py2pyd,py2pycd
Platform: any
Classifier: Development Status :: 5 - Production/Stable
Classifier: Environment :: Console
Classifier: Intended Audience :: Developers
Classifier: License :: OSI Approved :: GNU General Public License v3 (GPLv3)
Classifier: Natural Language :: English
Classifier: Natural Language :: Chinese (Simplified)
Classifier: Programming Language :: Python :: 3
Classifier: Topic :: Software Development :: Libraries :: Python Modules
Requires-Python: >=3.0
Requires-Dist: docopt (>=0.6.2)
Requires-Dist: cython (>=0.28.5)
